sayou/chunking/__init__.py
sayou/chunking/pipeline.py
sayou/chunking/core/exceptions.py
sayou/chunking/interfaces/base_splitter.py
sayou/chunking/plugins/audited_fixed_length_splitter.py
sayou/chunking/plugins/code_splitter.py
sayou/chunking/plugins/langchain_splitter.py
sayou/chunking/plugins/markdown_splitter.py
sayou/chunking/splitter/agentic_splitter.py
sayou/chunking/splitter/fixed_length_splitter.py
sayou/chunking/splitter/parent_document_splitter.py
sayou/chunking/splitter/recursive_splitter.py
sayou/chunking/splitter/semantic_splitter.py
sayou/chunking/splitter/structure_splitter.py
sayou/chunking/utils/text_segmenter.py
sayou_chunking-0.3.5.dist-info/METADATA
sayou_chunking-0.3.5.dist-info/WHEEL
sayou_chunking-0.3.5.dist-info/RECORD
